invenio_records_marc21/__init__.py
invenio_records_marc21/cli.py
invenio_records_marc21/config.py
invenio_records_marc21/errors.py
invenio_records_marc21/ext.py
invenio_records_marc21/proxies.py
invenio_records_marc21/tasks.py
invenio_records_marc21/utils.py
invenio_records_marc21/views.py
invenio_records_marc21/alembic/0058aec64e36_create_marc21_tables.py
invenio_records_marc21/alembic/109d88c6310c_create_records_marc21_branch.py
invenio_records_marc21/alembic/__init__.py
invenio_records_marc21/alembic/b9f2911d44c7_marc21_templates_add_updated.py
invenio_records_marc21/alembic/ed55fea7131e_add_deletion_status_to_marc21.py
invenio_records_marc21/data/example-record.xml
invenio_records_marc21/data/example-templates.json
invenio_records_marc21/data/fake-metadata.xml
invenio_records_marc21/data/fake-record.json
invenio_records_marc21/fixtures/__init__.py
invenio_records_marc21/fixtures/demo.py
invenio_records_marc21/fixtures/tasks.py
invenio_records_marc21/fixtures/templates.py
invenio_records_marc21/fixtures/utils.py
invenio_records_marc21/records/__init__.py
invenio_records_marc21/records/api.py
invenio_records_marc21/records/models.py
invenio_records_marc21/records/dumpers/__init__.py
invenio_records_marc21/records/dumpers/statistics.py
invenio_records_marc21/records/fields/resourcetype.py
invenio_records_marc21/records/jsonschemas/__init__.py
invenio_records_marc21/records/jsonschemas/marc21/definitions-v1.0.0.json
invenio_records_marc21/records/jsonschemas/marc21/marc21-structure-v1.0.0.json
invenio_records_marc21/records/jsonschemas/marc21/marc21-v1.0.0.json
invenio_records_marc21/records/jsonschemas/marc21/marc21-v2.0.0.json
invenio_records_marc21/records/jsonschemas/marc21/parent-v1.0.0.json
invenio_records_marc21/records/jsonschemas/marc21/parent-v2.0.0.json
invenio_records_marc21/records/mappings/__init__.py
invenio_records_marc21/records/mappings/os-v2/__init__.py
invenio_records_marc21/records/mappings/os-v2/marc21records/drafts/marc21-v1.0.0.json
invenio_records_marc21-0.27.1.dist-info/licenses/AUTHORS.rst
invenio_records_marc21-0.27.1.dist-info/licenses/LICENSE
invenio_records_marc21-0.27.1.dist-info/METADATA
invenio_records_marc21-0.27.1.dist-info/WHEEL
invenio_records_marc21-0.27.1.dist-info/entry_points.txt
invenio_records_marc21-0.27.1.dist-info/top_level.txt
invenio_records_marc21-0.27.1.dist-info/RECORD
