Metadata-Version: 2.4
Name: invenio-records-marc21
Version: 0.27.1
Summary: "Invenio Marc21 datamodel."
Home-page: https://github.com/tu-graz-library/invenio-records-marc21
Author: "Graz University of Technology"
Author-email: info@tugraz.at
License: MIT
Keywords: invenio Marc21 record
Platform: any
Classifier: Programming Language :: Python :: 3.12
Classifier: Programming Language :: Python :: 3.13
Classifier: Development Status :: 5 - Production/Stable
Requires-Python: >=3.12
License-File: LICENSE
License-File: AUTHORS.rst
Requires-Dist: arrow>=1.0.0
Requires-Dist: invenio-rdm-records>=19.0.0
Requires-Dist: invenio-stats>=1.0.0
Requires-Dist: fastjsonschema>=2.16.0
Requires-Dist: lxml>=4.6.2
Provides-Extra: tests
Requires-Dist: invenio-app<3.0.0,>=2.0.0; extra == "tests"
Requires-Dist: invenio-cache>=1.0.6; extra == "tests"
Requires-Dist: invenio-db<3.0.0,>=2.0.0; extra == "tests"
Requires-Dist: invenio-i18n<4.0.0,>=3.0.0; extra == "tests"
Requires-Dist: invenio-previewer<4.0.0,>=3.0.0; extra == "tests"
Requires-Dist: invenio-search[opensearch2]<4.0.0,>=3.0.0; extra == "tests"
Requires-Dist: pytest-black>=0.6.0; extra == "tests"
Requires-Dist: pytest-invenio<4.0.0,>=3.0.0; extra == "tests"
Requires-Dist: pytest-mock>=1.6.0; extra == "tests"
Requires-Dist: Sphinx>=4; extra == "tests"
Requires-Dist: sphinx-autodoc-typehints>=1.10.3; extra == "tests"
Dynamic: license-file
